llama_index/tools/google/__init__.py
llama_index/tools/google/calendar/__init__.py
llama_index/tools/google/calendar/base.py
llama_index/tools/google/gmail/__init__.py
llama_index/tools/google/gmail/base.py
llama_index/tools/google/search/__init__.py
llama_index/tools/google/search/base.py
llama_index_tools_google-0.6.2.dist-info/METADATA
llama_index_tools_google-0.6.2.dist-info/WHEEL
llama_index_tools_google-0.6.2.dist-info/licenses/LICENSE
llama_index_tools_google-0.6.2.dist-info/RECORD
