Metadata-Version: 2.4
Name: llama-index-tools-google
Version: 0.6.2
Summary: llama-index tools google integration
Author-email: Your Name <you@example.com>
Maintainer: ajhofmann
License-Expression: MIT
License-File: LICENSE
Keywords: email,gmail
Requires-Python: <4.0,>=3.9
Requires-Dist: beautifulsoup4<5,>=4.12.3
Requires-Dist: google-api-python-client<3,>=2.115.0
Requires-Dist: google-auth-httplib2<0.3,>=0.2.0
Requires-Dist: google-auth-oauthlib<2,>=1.2.0
Requires-Dist: llama-index-core<0.15,>=0.13.0
